sawnergy/__init__.py
sawnergy/logging_util.py
sawnergy/sawnergy_util.py
sawnergy/embedding/SGNS_pml.py
sawnergy/embedding/SGNS_torch.py
sawnergy/embedding/__init__.py
sawnergy/embedding/embedder.py
sawnergy/embedding/visualizer.py
sawnergy/rin/__init__.py
sawnergy/rin/rin_builder.py
sawnergy/rin/rin_util.py
sawnergy/visual/__init__.py
sawnergy/visual/visualizer.py
sawnergy/visual/visualizer_util.py
sawnergy/walks/__init__.py
sawnergy/walks/walker.py
sawnergy/walks/walker_util.py
sawnergy-1.1.6.dist-info/licenses/LICENSE
sawnergy-1.1.6.dist-info/licenses/NOTICE
sawnergy-1.1.6.dist-info/METADATA
sawnergy-1.1.6.dist-info/WHEEL
sawnergy-1.1.6.dist-info/top_level.txt
sawnergy-1.1.6.dist-info/RECORD
