Metadata-Version: 2.4
Name: sawnergy
Version: 1.1.6
Summary: Toolkit for transforming molecular dynamics (MD) trajectories into rich graph representations
Home-page: https://github.com/Yehor-Mishchyriak/SAWNERGY
Author: Yehor Mishchyriak
License: Apache-2.0
Project-URL: Source, https://github.com/Yehor-Mishchyriak/SAWNERGY
Project-URL: Tracker, https://github.com/Yehor-Mishchyriak/SAWNERGY/issues
Classifier: Programming Language :: Python :: 3
Classifier: License :: OSI Approved :: Apache Software License
Classifier: Operating System :: OS Independent
Requires-Python: >=3.11
License-File: LICENSE
License-File: NOTICE
Requires-Dist: numpy>=2.0
Requires-Dist: zarr>=3.0
Requires-Dist: threadpoolctl>=3.0
Requires-Dist: matplotlib>=3.7
Requires-Dist: psutil>=5.9
Requires-Dist: ym-pure-ml==1.2.7
Dynamic: author
Dynamic: classifier
Dynamic: description
Dynamic: description-content-type
Dynamic: home-page
Dynamic: license
Dynamic: license-file
Dynamic: project-url
Dynamic: requires-dist
Dynamic: requires-python
Dynamic: summary
